{
  "active_plan": "/mnt/c/Users/ol_ta/desktop/java_reports/.sisyphus/plans/test-reporting-system.md",
  "started_at": "2026-04-26T12:07:28.667Z",
  "session_ids": [
    "ses_2369d9145ffeXT8OqFUzbKdEAZ",
    "ses_236450bceffevTmPs7V4Hi6IlK",
    "ses_2364479aeffe1SPKGj7AGCbjNf",
    "ses_236440f68ffevRVGLYh72btHp6",
    "ses_23643b211ffeWhFJPD0eWOjrTJ",
    "ses_236280c08ffer0Bj0F1DrvSu7N",
    "ses_23627a2c3ffewUKxp040Qo3LUC",
    "ses_2361ddd38ffeHmMh5wlnklwP3u",
    "ses_236168fa4ffeyofFTbwG6ZQqMb",
    "ses_236163181ffedVE5hgK4lPvUtg",
    "ses_23615e27effee2z4E7D3bQNK6H",
    "ses_236158277ffeaX8X2KOgT62Q05",
    "ses_2361517b7ffej3RlrP9z0Cd7pT",
    "ses_235ffbc0bffeZbLCJHZhqQukII",
    "ses_235ff76b5ffey32amkp4c8PFTk",
    "ses_235ff2b25ffe6e3IC3wXLchoDD",
    "ses_235f8c628ffex0zuGELdLVpIrD",
    "ses_235f88718ffeQfkY267Biisoqx",
    "ses_235f50ec5ffe9LwZe43FZ3kqn9",
    "ses_235f4efabffe0Y4qYFP6rgOus8",
    "ses_235f4baa2ffeT4wwX794dHSUbm",
    "ses_235f47fffffeTLfKBLxKl4zlwa",
    "ses_235ec613fffeopYoicqIPGBz1k",
    "ses_235e8ed97ffe4KX2lQgVdhcII7",
    "ses_235e8d122ffefpgvIH4qr9T8xS",
    "ses_235e8bc2bffe6talSGRfXeWYLv"
  ],
  "plan_name": "test-reporting-system",
  "session_origins": {
    "ses_2369d9145ffeXT8OqFUzbKdEAZ": "direct",
    "ses_236450bceffevTmPs7V4Hi6IlK": "appended",
    "ses_2364479aeffe1SPKGj7AGCbjNf": "appended",
    "ses_236440f68ffevRVGLYh72btHp6": "appended",
    "ses_23643b211ffeWhFJPD0eWOjrTJ": "appended",
    "ses_236280c08ffer0Bj0F1DrvSu7N": "appended",
    "ses_23627a2c3ffewUKxp040Qo3LUC": "appended",
    "ses_2361ddd38ffeHmMh5wlnklwP3u": "appended",
    "ses_236168fa4ffeyofFTbwG6ZQqMb": "appended",
    "ses_236163181ffedVE5hgK4lPvUtg": "appended",
    "ses_23615e27effee2z4E7D3bQNK6H": "appended",
    "ses_236158277ffeaX8X2KOgT62Q05": "appended",
    "ses_2361517b7ffej3RlrP9z0Cd7pT": "appended",
    "ses_235ffbc0bffeZbLCJHZhqQukII": "appended",
    "ses_235ff76b5ffey32amkp4c8PFTk": "appended",
    "ses_235ff2b25ffe6e3IC3wXLchoDD": "appended",
    "ses_235f8c628ffex0zuGELdLVpIrD": "appended",
    "ses_235f88718ffeQfkY267Biisoqx": "appended",
    "ses_235f50ec5ffe9LwZe43FZ3kqn9": "appended",
    "ses_235f4efabffe0Y4qYFP6rgOus8": "appended",
    "ses_235f4baa2ffeT4wwX794dHSUbm": "appended",
    "ses_235f47fffffeTLfKBLxKl4zlwa": "appended",
    "ses_235ec613fffeopYoicqIPGBz1k": "appended",
    "ses_235e8ed97ffe4KX2lQgVdhcII7": "appended",
    "ses_235e8d122ffefpgvIH4qr9T8xS": "appended",
    "ses_235e8bc2bffe6talSGRfXeWYLv": "appended"
  },
  "task_sessions": {}
}